etl/__init__.py
etl/cli/__init__.py
etl/cli/app.py
etl/cli/main.py
etl/config/__init__.py
etl/config/app.py
etl/config/auth_type.py
etl/config/database.py
etl/config/settings.py
etl/config/yaml.py
etl/models/file_parsing_result.py
etl/paths.py
etl/pipeline.py
etl/py.typed
etl/std/__init__.py
etl/std/error.py
etl/std/error_results.py
etl/std/exceptions.py
etl/std/result.py
etl_toolkit-0.0.2.dist-info/LICENSE
etl_toolkit-0.0.2.dist-info/METADATA
etl_toolkit-0.0.2.dist-info/WHEEL
etl_toolkit-0.0.2.dist-info/entry_points.txt
etl_toolkit-0.0.2.dist-info/RECORD
